{
    "Name": "OPP_2D_10_2s_5I_0W",
    "Container": {
        "Dx": 100,
        "Dy": 100,
        "Area": 10000
    },
    "Items": [
        {
            "X": 0,
            "Y": 0,
            "Dx": 27,
            "Dy": 26,
            "Area": 702,
            "ExternId": 0
        },
        {
            "X": 0,
            "Y": 0,
            "Dx": 10,
            "Dy": 19,
            "Area": 190,
            "ExternId": 1
        },
        {
            "X": 0,
            "Y": 0,
            "Dx": 30,
            "Dy": 43,
            "Area": 1290,
            "ExternId": 2
        },
        {
            "X": 0,
            "Y": 0,
            "Dx": 17,
            "Dy": 13,
            "Area": 221,
            "ExternId": 3
        },
        {
            "X": 0,
            "Y": 0,
            "Dx": 42,
            "Dy": 34,
            "Area": 1428,
            "ExternId": 4
        },
        {
            "X": 0,
            "Y": 0,
            "Dx": 42,
            "Dy": 46,
            "Area": 1932,
            "ExternId": 5
        },
        {
            "X": 0,
            "Y": 0,
            "Dx": 5,
            "Dy": 10,
            "Area": 50,
            "ExternId": 6
        },
        {
            "X": 0,
            "Y": 0,
            "Dx": 52,
            "Dy": 31,
            "Area": 1612,
            "ExternId": 7
        },
        {
            "X": 0,
            "Y": 0,
            "Dx": 53,
            "Dy": 35,
            "Area": 1855,
            "ExternId": 8
        },
        {
            "X": 0,
            "Y": 0,
            "Dx": 17,
            "Dy": 29,
            "Area": 493,
            "ExternId": 9
        }
    ]
}