{
    "Name": "OPP_2D_25_2s_3I_40W",
    "Container": {
        "Dx": 100,
        "Dy": 100,
        "Area": 10000
    },
    "Items": [
        {
            "X": 0,
            "Y": 0,
            "Dx": 2,
            "Dy": 2,
            "Area": 4,
            "ExternId": 0
        },
        {
            "X": 0,
            "Y": 0,
            "Dx": 15,
            "Dy": 8,
            "Area": 120,
            "ExternId": 1
        },
        {
            "X": 0,
            "Y": 0,
            "Dx": 19,
            "Dy": 21,
            "Area": 399,
            "ExternId": 2
        },
        {
            "X": 0,
            "Y": 0,
            "Dx": 4,
            "Dy": 7,
            "Area": 28,
            "ExternId": 3
        },
        {
            "X": 0,
            "Y": 0,
            "Dx": 19,
            "Dy": 22,
            "Area": 418,
            "ExternId": 4
        },
        {
            "X": 0,
            "Y": 0,
            "Dx": 36,
            "Dy": 26,
            "Area": 936,
            "ExternId": 5
        },
        {
            "X": 0,
            "Y": 0,
            "Dx": 29,
            "Dy": 17,
            "Area": 493,
            "ExternId": 6
        },
        {
            "X": 0,
            "Y": 0,
            "Dx": 9,
            "Dy": 7,
            "Area": 63,
            "ExternId": 7
        },
        {
            "X": 0,
            "Y": 0,
            "Dx": 24,
            "Dy": 14,
            "Area": 336,
            "ExternId": 8
        },
        {
            "X": 0,
            "Y": 0,
            "Dx": 6,
            "Dy": 4,
            "Area": 24,
            "ExternId": 9
        },
        {
            "X": 0,
            "Y": 0,
            "Dx": 17,
            "Dy": 16,
            "Area": 272,
            "ExternId": 10
        },
        {
            "X": 0,
            "Y": 0,
            "Dx": 2,
            "Dy": 2,
            "Area": 4,
            "ExternId": 11
        },
        {
            "X": 0,
            "Y": 0,
            "Dx": 14,
            "Dy": 16,
            "Area": 224,
            "ExternId": 12
        },
        {
            "X": 0,
            "Y": 0,
            "Dx": 20,
            "Dy": 18,
            "Area": 360,
            "ExternId": 13
        },
        {
            "X": 0,
            "Y": 0,
            "Dx": 5,
            "Dy": 10,
            "Area": 50,
            "ExternId": 14
        },
        {
            "X": 0,
            "Y": 0,
            "Dx": 18,
            "Dy": 13,
            "Area": 234,
            "ExternId": 15
        },
        {
            "X": 0,
            "Y": 0,
            "Dx": 8,
            "Dy": 8,
            "Area": 64,
            "ExternId": 16
        },
        {
            "X": 0,
            "Y": 0,
            "Dx": 11,
            "Dy": 17,
            "Area": 187,
            "ExternId": 17
        },
        {
            "X": 0,
            "Y": 0,
            "Dx": 23,
            "Dy": 13,
            "Area": 299,
            "ExternId": 18
        },
        {
            "X": 0,
            "Y": 0,
            "Dx": 9,
            "Dy": 9,
            "Area": 81,
            "ExternId": 19
        },
        {
            "X": 0,
            "Y": 0,
            "Dx": 17,
            "Dy": 28,
            "Area": 476,
            "ExternId": 20
        },
        {
            "X": 0,
            "Y": 0,
            "Dx": 10,
            "Dy": 5,
            "Area": 50,
            "ExternId": 21
        },
        {
            "X": 0,
            "Y": 0,
            "Dx": 16,
            "Dy": 11,
            "Area": 176,
            "ExternId": 22
        },
        {
            "X": 0,
            "Y": 0,
            "Dx": 18,
            "Dy": 12,
            "Area": 216,
            "ExternId": 23
        },
        {
            "X": 0,
            "Y": 0,
            "Dx": 12,
            "Dy": 14,
            "Area": 168,
            "ExternId": 24
        }
    ]
}