{
    "Name": "OPP_2D_15_2s_1I_8W",
    "Container": {
        "Dx": 100,
        "Dy": 100,
        "Area": 10000
    },
    "Items": [
        {
            "X": 0,
            "Y": 0,
            "Dx": 13,
            "Dy": 9,
            "Area": 117,
            "ExternId": 0
        },
        {
            "X": 0,
            "Y": 0,
            "Dx": 22,
            "Dy": 16,
            "Area": 352,
            "ExternId": 1
        },
        {
            "X": 0,
            "Y": 0,
            "Dx": 23,
            "Dy": 35,
            "Area": 805,
            "ExternId": 2
        },
        {
            "X": 0,
            "Y": 0,
            "Dx": 10,
            "Dy": 13,
            "Area": 130,
            "ExternId": 3
        },
        {
            "X": 0,
            "Y": 0,
            "Dx": 16,
            "Dy": 32,
            "Area": 512,
            "ExternId": 4
        },
        {
            "X": 0,
            "Y": 0,
            "Dx": 23,
            "Dy": 21,
            "Area": 483,
            "ExternId": 5
        },
        {
            "X": 0,
            "Y": 0,
            "Dx": 20,
            "Dy": 32,
            "Area": 640,
            "ExternId": 6
        },
        {
            "X": 0,
            "Y": 0,
            "Dx": 22,
            "Dy": 16,
            "Area": 352,
            "ExternId": 7
        },
        {
            "X": 0,
            "Y": 0,
            "Dx": 42,
            "Dy": 34,
            "Area": 1428,
            "ExternId": 8
        },
        {
            "X": 0,
            "Y": 0,
            "Dx": 42,
            "Dy": 26,
            "Area": 1092,
            "ExternId": 9
        },
        {
            "X": 0,
            "Y": 0,
            "Dx": 28,
            "Dy": 39,
            "Area": 1092,
            "ExternId": 10
        },
        {
            "X": 0,
            "Y": 0,
            "Dx": 13,
            "Dy": 19,
            "Area": 247,
            "ExternId": 11
        },
        {
            "X": 0,
            "Y": 0,
            "Dx": 16,
            "Dy": 11,
            "Area": 176,
            "ExternId": 12
        },
        {
            "X": 0,
            "Y": 0,
            "Dx": 24,
            "Dy": 18,
            "Area": 432,
            "ExternId": 13
        },
        {
            "X": 0,
            "Y": 0,
            "Dx": 40,
            "Dy": 24,
            "Area": 960,
            "ExternId": 14
        }
    ]
}