{
    "Name": "OPP_2D_20_3s_9I_24W",
    "Container": {
        "Dx": 1000,
        "Dy": 1000,
        "Area": 1000000
    },
    "Items": [
        {
            "X": 0,
            "Y": 0,
            "Dx": 99,
            "Dy": 99,
            "Area": 9801,
            "ExternId": 0
        },
        {
            "X": 0,
            "Y": 0,
            "Dx": 150,
            "Dy": 262,
            "Area": 39300,
            "ExternId": 1
        },
        {
            "X": 0,
            "Y": 0,
            "Dx": 275,
            "Dy": 283,
            "Area": 77825,
            "ExternId": 2
        },
        {
            "X": 0,
            "Y": 0,
            "Dx": 165,
            "Dy": 209,
            "Area": 34485,
            "ExternId": 3
        },
        {
            "X": 0,
            "Y": 0,
            "Dx": 181,
            "Dy": 135,
            "Area": 24435,
            "ExternId": 4
        },
        {
            "X": 0,
            "Y": 0,
            "Dx": 94,
            "Dy": 100,
            "Area": 9400,
            "ExternId": 5
        },
        {
            "X": 0,
            "Y": 0,
            "Dx": 100,
            "Dy": 177,
            "Area": 17700,
            "ExternId": 6
        },
        {
            "X": 0,
            "Y": 0,
            "Dx": 259,
            "Dy": 127,
            "Area": 32893,
            "ExternId": 7
        },
        {
            "X": 0,
            "Y": 0,
            "Dx": 67,
            "Dy": 160,
            "Area": 10720,
            "ExternId": 8
        },
        {
            "X": 0,
            "Y": 0,
            "Dx": 507,
            "Dy": 236,
            "Area": 119652,
            "ExternId": 9
        },
        {
            "X": 0,
            "Y": 0,
            "Dx": 267,
            "Dy": 338,
            "Area": 90246,
            "ExternId": 10
        },
        {
            "X": 0,
            "Y": 0,
            "Dx": 116,
            "Dy": 280,
            "Area": 32480,
            "ExternId": 11
        },
        {
            "X": 0,
            "Y": 0,
            "Dx": 102,
            "Dy": 306,
            "Area": 31212,
            "ExternId": 12
        },
        {
            "X": 0,
            "Y": 0,
            "Dx": 310,
            "Dy": 118,
            "Area": 36580,
            "ExternId": 13
        },
        {
            "X": 0,
            "Y": 0,
            "Dx": 113,
            "Dy": 70,
            "Area": 7910,
            "ExternId": 14
        },
        {
            "X": 0,
            "Y": 0,
            "Dx": 294,
            "Dy": 191,
            "Area": 56154,
            "ExternId": 15
        },
        {
            "X": 0,
            "Y": 0,
            "Dx": 171,
            "Dy": 186,
            "Area": 31806,
            "ExternId": 16
        },
        {
            "X": 0,
            "Y": 0,
            "Dx": 284,
            "Dy": 159,
            "Area": 45156,
            "ExternId": 17
        },
        {
            "X": 0,
            "Y": 0,
            "Dx": 44,
            "Dy": 62,
            "Area": 2728,
            "ExternId": 18
        },
        {
            "X": 0,
            "Y": 0,
            "Dx": 341,
            "Dy": 134,
            "Area": 45694,
            "ExternId": 19
        }
    ]
}