{
    "Name": "OPP_2D_20_20s_5I_14W",
    "Container": {
        "Dx": 1000,
        "Dy": 1000,
        "Area": 1000000
    },
    "Items": [
        {
            "X": 0,
            "Y": 0,
            "Dx": 366,
            "Dy": 173,
            "Area": 63318,
            "ExternId": 0
        },
        {
            "X": 0,
            "Y": 0,
            "Dx": 609,
            "Dy": 66,
            "Area": 40194,
            "ExternId": 1
        },
        {
            "X": 0,
            "Y": 0,
            "Dx": 342,
            "Dy": 18,
            "Area": 6156,
            "ExternId": 2
        },
        {
            "X": 0,
            "Y": 0,
            "Dx": 155,
            "Dy": 478,
            "Area": 74090,
            "ExternId": 3
        },
        {
            "X": 0,
            "Y": 0,
            "Dx": 304,
            "Dy": 190,
            "Area": 57760,
            "ExternId": 4
        },
        {
            "X": 0,
            "Y": 0,
            "Dx": 332,
            "Dy": 71,
            "Area": 23572,
            "ExternId": 5
        },
        {
            "X": 0,
            "Y": 0,
            "Dx": 510,
            "Dy": 95,
            "Area": 48450,
            "ExternId": 6
        },
        {
            "X": 0,
            "Y": 0,
            "Dx": 241,
            "Dy": 24,
            "Area": 5784,
            "ExternId": 7
        },
        {
            "X": 0,
            "Y": 0,
            "Dx": 527,
            "Dy": 96,
            "Area": 50592,
            "ExternId": 8
        },
        {
            "X": 0,
            "Y": 0,
            "Dx": 110,
            "Dy": 160,
            "Area": 17600,
            "ExternId": 9
        },
        {
            "X": 0,
            "Y": 0,
            "Dx": 43,
            "Dy": 39,
            "Area": 1677,
            "ExternId": 10
        },
        {
            "X": 0,
            "Y": 0,
            "Dx": 111,
            "Dy": 149,
            "Area": 16539,
            "ExternId": 11
        },
        {
            "X": 0,
            "Y": 0,
            "Dx": 497,
            "Dy": 64,
            "Area": 31808,
            "ExternId": 12
        },
        {
            "X": 0,
            "Y": 0,
            "Dx": 677,
            "Dy": 90,
            "Area": 60930,
            "ExternId": 13
        },
        {
            "X": 0,
            "Y": 0,
            "Dx": 271,
            "Dy": 273,
            "Area": 73983,
            "ExternId": 14
        },
        {
            "X": 0,
            "Y": 0,
            "Dx": 66,
            "Dy": 887,
            "Area": 58542,
            "ExternId": 15
        },
        {
            "X": 0,
            "Y": 0,
            "Dx": 184,
            "Dy": 554,
            "Area": 101936,
            "ExternId": 16
        },
        {
            "X": 0,
            "Y": 0,
            "Dx": 347,
            "Dy": 110,
            "Area": 38170,
            "ExternId": 17
        },
        {
            "X": 0,
            "Y": 0,
            "Dx": 191,
            "Dy": 215,
            "Area": 41065,
            "ExternId": 18
        },
        {
            "X": 0,
            "Y": 0,
            "Dx": 272,
            "Dy": 159,
            "Area": 43248,
            "ExternId": 19
        }
    ]
}