{
    "Name": "OPP_2D_20_3s_7I_0W",
    "Container": {
        "Dx": 1000,
        "Dy": 1000,
        "Area": 1000000
    },
    "Items": [
        {
            "X": 0,
            "Y": 0,
            "Dx": 120,
            "Dy": 207,
            "Area": 24840,
            "ExternId": 0
        },
        {
            "X": 0,
            "Y": 0,
            "Dx": 368,
            "Dy": 282,
            "Area": 103776,
            "ExternId": 1
        },
        {
            "X": 0,
            "Y": 0,
            "Dx": 139,
            "Dy": 239,
            "Area": 33221,
            "ExternId": 2
        },
        {
            "X": 0,
            "Y": 0,
            "Dx": 157,
            "Dy": 172,
            "Area": 27004,
            "ExternId": 3
        },
        {
            "X": 0,
            "Y": 0,
            "Dx": 88,
            "Dy": 256,
            "Area": 22528,
            "ExternId": 4
        },
        {
            "X": 0,
            "Y": 0,
            "Dx": 45,
            "Dy": 127,
            "Area": 5715,
            "ExternId": 5
        },
        {
            "X": 0,
            "Y": 0,
            "Dx": 53,
            "Dy": 151,
            "Area": 8003,
            "ExternId": 6
        },
        {
            "X": 0,
            "Y": 0,
            "Dx": 78,
            "Dy": 224,
            "Area": 17472,
            "ExternId": 7
        },
        {
            "X": 0,
            "Y": 0,
            "Dx": 162,
            "Dy": 76,
            "Area": 12312,
            "ExternId": 8
        },
        {
            "X": 0,
            "Y": 0,
            "Dx": 153,
            "Dy": 372,
            "Area": 56916,
            "ExternId": 9
        },
        {
            "X": 0,
            "Y": 0,
            "Dx": 46,
            "Dy": 36,
            "Area": 1656,
            "ExternId": 10
        },
        {
            "X": 0,
            "Y": 0,
            "Dx": 89,
            "Dy": 164,
            "Area": 14596,
            "ExternId": 11
        },
        {
            "X": 0,
            "Y": 0,
            "Dx": 288,
            "Dy": 687,
            "Area": 197856,
            "ExternId": 12
        },
        {
            "X": 0,
            "Y": 0,
            "Dx": 295,
            "Dy": 532,
            "Area": 156940,
            "ExternId": 13
        },
        {
            "X": 0,
            "Y": 0,
            "Dx": 235,
            "Dy": 272,
            "Area": 63920,
            "ExternId": 14
        },
        {
            "X": 0,
            "Y": 0,
            "Dx": 139,
            "Dy": 340,
            "Area": 47260,
            "ExternId": 15
        },
        {
            "X": 0,
            "Y": 0,
            "Dx": 276,
            "Dy": 115,
            "Area": 31740,
            "ExternId": 16
        },
        {
            "X": 0,
            "Y": 0,
            "Dx": 189,
            "Dy": 497,
            "Area": 93933,
            "ExternId": 17
        },
        {
            "X": 0,
            "Y": 0,
            "Dx": 159,
            "Dy": 124,
            "Area": 19716,
            "ExternId": 18
        },
        {
            "X": 0,
            "Y": 0,
            "Dx": 308,
            "Dy": 182,
            "Area": 56056,
            "ExternId": 19
        }
    ]
}