{
    "Name": "OPP_2D_20_3s_1I_30W",
    "Container": {
        "Dx": 1000,
        "Dy": 1000,
        "Area": 1000000
    },
    "Items": [
        {
            "X": 0,
            "Y": 0,
            "Dx": 54,
            "Dy": 115,
            "Area": 6210,
            "ExternId": 0
        },
        {
            "X": 0,
            "Y": 0,
            "Dx": 150,
            "Dy": 248,
            "Area": 37200,
            "ExternId": 1
        },
        {
            "X": 0,
            "Y": 0,
            "Dx": 158,
            "Dy": 134,
            "Area": 21172,
            "ExternId": 2
        },
        {
            "X": 0,
            "Y": 0,
            "Dx": 131,
            "Dy": 160,
            "Area": 20960,
            "ExternId": 3
        },
        {
            "X": 0,
            "Y": 0,
            "Dx": 212,
            "Dy": 303,
            "Area": 64236,
            "ExternId": 4
        },
        {
            "X": 0,
            "Y": 0,
            "Dx": 345,
            "Dy": 266,
            "Area": 91770,
            "ExternId": 5
        },
        {
            "X": 0,
            "Y": 0,
            "Dx": 51,
            "Dy": 59,
            "Area": 3009,
            "ExternId": 6
        },
        {
            "X": 0,
            "Y": 0,
            "Dx": 18,
            "Dy": 38,
            "Area": 684,
            "ExternId": 7
        },
        {
            "X": 0,
            "Y": 0,
            "Dx": 264,
            "Dy": 89,
            "Area": 23496,
            "ExternId": 8
        },
        {
            "X": 0,
            "Y": 0,
            "Dx": 189,
            "Dy": 202,
            "Area": 38178,
            "ExternId": 9
        },
        {
            "X": 0,
            "Y": 0,
            "Dx": 119,
            "Dy": 62,
            "Area": 7378,
            "ExternId": 10
        },
        {
            "X": 0,
            "Y": 0,
            "Dx": 277,
            "Dy": 111,
            "Area": 30747,
            "ExternId": 11
        },
        {
            "X": 0,
            "Y": 0,
            "Dx": 280,
            "Dy": 128,
            "Area": 35840,
            "ExternId": 12
        },
        {
            "X": 0,
            "Y": 0,
            "Dx": 190,
            "Dy": 330,
            "Area": 62700,
            "ExternId": 13
        },
        {
            "X": 0,
            "Y": 0,
            "Dx": 431,
            "Dy": 158,
            "Area": 68098,
            "ExternId": 14
        },
        {
            "X": 0,
            "Y": 0,
            "Dx": 205,
            "Dy": 158,
            "Area": 32390,
            "ExternId": 15
        },
        {
            "X": 0,
            "Y": 0,
            "Dx": 13,
            "Dy": 27,
            "Area": 351,
            "ExternId": 16
        },
        {
            "X": 0,
            "Y": 0,
            "Dx": 107,
            "Dy": 259,
            "Area": 27713,
            "ExternId": 17
        },
        {
            "X": 0,
            "Y": 0,
            "Dx": 565,
            "Dy": 196,
            "Area": 110740,
            "ExternId": 18
        },
        {
            "X": 0,
            "Y": 0,
            "Dx": 195,
            "Dy": 71,
            "Area": 13845,
            "ExternId": 19
        }
    ]
}