{
    "Name": "OPP_2D_20_1s_5I_30W",
    "Container": {
        "Dx": 1000,
        "Dy": 1000,
        "Area": 1000000
    },
    "Items": [
        {
            "X": 0,
            "Y": 0,
            "Dx": 338,
            "Dy": 338,
            "Area": 114244,
            "ExternId": 0
        },
        {
            "X": 0,
            "Y": 0,
            "Dx": 89,
            "Dy": 89,
            "Area": 7921,
            "ExternId": 1
        },
        {
            "X": 0,
            "Y": 0,
            "Dx": 126,
            "Dy": 126,
            "Area": 15876,
            "ExternId": 2
        },
        {
            "X": 0,
            "Y": 0,
            "Dx": 206,
            "Dy": 206,
            "Area": 42436,
            "ExternId": 3
        },
        {
            "X": 0,
            "Y": 0,
            "Dx": 70,
            "Dy": 70,
            "Area": 4900,
            "ExternId": 4
        },
        {
            "X": 0,
            "Y": 0,
            "Dx": 130,
            "Dy": 130,
            "Area": 16900,
            "ExternId": 5
        },
        {
            "X": 0,
            "Y": 0,
            "Dx": 118,
            "Dy": 118,
            "Area": 13924,
            "ExternId": 6
        },
        {
            "X": 0,
            "Y": 0,
            "Dx": 190,
            "Dy": 190,
            "Area": 36100,
            "ExternId": 7
        },
        {
            "X": 0,
            "Y": 0,
            "Dx": 151,
            "Dy": 151,
            "Area": 22801,
            "ExternId": 8
        },
        {
            "X": 0,
            "Y": 0,
            "Dx": 74,
            "Dy": 74,
            "Area": 5476,
            "ExternId": 9
        },
        {
            "X": 0,
            "Y": 0,
            "Dx": 19,
            "Dy": 19,
            "Area": 361,
            "ExternId": 10
        },
        {
            "X": 0,
            "Y": 0,
            "Dx": 272,
            "Dy": 272,
            "Area": 73984,
            "ExternId": 11
        },
        {
            "X": 0,
            "Y": 0,
            "Dx": 192,
            "Dy": 192,
            "Area": 36864,
            "ExternId": 12
        },
        {
            "X": 0,
            "Y": 0,
            "Dx": 229,
            "Dy": 229,
            "Area": 52441,
            "ExternId": 13
        },
        {
            "X": 0,
            "Y": 0,
            "Dx": 195,
            "Dy": 195,
            "Area": 38025,
            "ExternId": 14
        },
        {
            "X": 0,
            "Y": 0,
            "Dx": 257,
            "Dy": 257,
            "Area": 66049,
            "ExternId": 15
        },
        {
            "X": 0,
            "Y": 0,
            "Dx": 218,
            "Dy": 218,
            "Area": 47524,
            "ExternId": 16
        },
        {
            "X": 0,
            "Y": 0,
            "Dx": 262,
            "Dy": 262,
            "Area": 68644,
            "ExternId": 17
        },
        {
            "X": 0,
            "Y": 0,
            "Dx": 30,
            "Dy": 30,
            "Area": 900,
            "ExternId": 18
        },
        {
            "X": 0,
            "Y": 0,
            "Dx": 179,
            "Dy": 179,
            "Area": 32041,
            "ExternId": 19
        }
    ]
}