{
    "Name": "OPP_2D_20_1s_10I_2W",
    "Container": {
        "Dx": 1000,
        "Dy": 1000,
        "Area": 1000000
    },
    "Items": [
        {
            "X": 0,
            "Y": 0,
            "Dx": 153,
            "Dy": 153,
            "Area": 23409,
            "ExternId": 0
        },
        {
            "X": 0,
            "Y": 0,
            "Dx": 72,
            "Dy": 72,
            "Area": 5184,
            "ExternId": 1
        },
        {
            "X": 0,
            "Y": 0,
            "Dx": 62,
            "Dy": 62,
            "Area": 3844,
            "ExternId": 2
        },
        {
            "X": 0,
            "Y": 0,
            "Dx": 233,
            "Dy": 233,
            "Area": 54289,
            "ExternId": 3
        },
        {
            "X": 0,
            "Y": 0,
            "Dx": 143,
            "Dy": 143,
            "Area": 20449,
            "ExternId": 4
        },
        {
            "X": 0,
            "Y": 0,
            "Dx": 146,
            "Dy": 146,
            "Area": 21316,
            "ExternId": 5
        },
        {
            "X": 0,
            "Y": 0,
            "Dx": 265,
            "Dy": 265,
            "Area": 70225,
            "ExternId": 6
        },
        {
            "X": 0,
            "Y": 0,
            "Dx": 298,
            "Dy": 298,
            "Area": 88804,
            "ExternId": 7
        },
        {
            "X": 0,
            "Y": 0,
            "Dx": 123,
            "Dy": 123,
            "Area": 15129,
            "ExternId": 8
        },
        {
            "X": 0,
            "Y": 0,
            "Dx": 372,
            "Dy": 372,
            "Area": 138384,
            "ExternId": 9
        },
        {
            "X": 0,
            "Y": 0,
            "Dx": 144,
            "Dy": 144,
            "Area": 20736,
            "ExternId": 10
        },
        {
            "X": 0,
            "Y": 0,
            "Dx": 333,
            "Dy": 333,
            "Area": 110889,
            "ExternId": 11
        },
        {
            "X": 0,
            "Y": 0,
            "Dx": 33,
            "Dy": 33,
            "Area": 1089,
            "ExternId": 12
        },
        {
            "X": 0,
            "Y": 0,
            "Dx": 244,
            "Dy": 244,
            "Area": 59536,
            "ExternId": 13
        },
        {
            "X": 0,
            "Y": 0,
            "Dx": 148,
            "Dy": 148,
            "Area": 21904,
            "ExternId": 14
        },
        {
            "X": 0,
            "Y": 0,
            "Dx": 170,
            "Dy": 170,
            "Area": 28900,
            "ExternId": 15
        },
        {
            "X": 0,
            "Y": 0,
            "Dx": 334,
            "Dy": 334,
            "Area": 111556,
            "ExternId": 16
        },
        {
            "X": 0,
            "Y": 0,
            "Dx": 208,
            "Dy": 208,
            "Area": 43264,
            "ExternId": 17
        },
        {
            "X": 0,
            "Y": 0,
            "Dx": 107,
            "Dy": 107,
            "Area": 11449,
            "ExternId": 18
        },
        {
            "X": 0,
            "Y": 0,
            "Dx": 356,
            "Dy": 356,
            "Area": 126736,
            "ExternId": 19
        }
    ]
}